nvme/__init__.py
nvme/cmd/__init__.py
nvme/cmd/admin/identify.py
nvme/cmd/admin/logpage.py
nvme/cmd/completion.py
nvme/driver/__init__.py
nvme/driver/linuxioctl.py
nvme/util.py
nvme-0.2.0.dist-info/entry_points.txt
nvme-0.2.0.dist-info/LICENSE
nvme-0.2.0.dist-info/WHEEL
nvme-0.2.0.dist-info/METADATA
nvme-0.2.0.dist-info/RECORD
