Metadata-Version: 2.1
Name: nvme
Version: 0.2.0
Summary: 
License: MIT
Author: Gregory C. Oakes
Author-email: gregcoakes@gmail.com
Requires-Python: >=3.6.0,<4.0.0
Classifier: License :: OSI Approved :: MIT License
Classifier: Programming Language :: Python :: 3
Classifier: Programming Language :: Python :: 3.6
Classifier: Programming Language :: Python :: 3.7
Classifier: Programming Language :: Python :: 3.8
Classifier: Programming Language :: Python :: 3.9
Requires-Dist: importlib-metadata (>=4.8.1,<5.0.0); python_version >= "3.6" and python_version < "3.8"
